ipvanish_bundle/__init__.py
ipvanish_bundle/bundle/__init__.py
ipvanish_bundle/bundle/darwin/AE.py
ipvanish_bundle/bundle/darwin/AL.py
ipvanish_bundle/bundle/darwin/AT.py
ipvanish_bundle/bundle/darwin/AU.py
ipvanish_bundle/bundle/darwin/BE.py
ipvanish_bundle/bundle/darwin/BG.py
ipvanish_bundle/bundle/darwin/BR.py
ipvanish_bundle/bundle/darwin/CA.py
ipvanish_bundle/bundle/darwin/CH.py
ipvanish_bundle/bundle/darwin/CN.py
ipvanish_bundle/bundle/darwin/CR.py
ipvanish_bundle/bundle/darwin/CY.py
ipvanish_bundle/bundle/darwin/CZ.py
ipvanish_bundle/bundle/darwin/DE.py
ipvanish_bundle/bundle/darwin/DK.py
ipvanish_bundle/bundle/darwin/EE.py
ipvanish_bundle/bundle/darwin/ES.py
ipvanish_bundle/bundle/darwin/FI.py
ipvanish_bundle/bundle/darwin/FR.py
ipvanish_bundle/bundle/darwin/GR.py
ipvanish_bundle/bundle/darwin/HK.py
ipvanish_bundle/bundle/darwin/HR.py
ipvanish_bundle/bundle/darwin/HU.py
ipvanish_bundle/bundle/darwin/IE.py
ipvanish_bundle/bundle/darwin/IL.py
ipvanish_bundle/bundle/darwin/IN.py
ipvanish_bundle/bundle/darwin/IT.py
ipvanish_bundle/bundle/darwin/JP.py
ipvanish_bundle/bundle/darwin/KR.py
ipvanish_bundle/bundle/darwin/LT.py
ipvanish_bundle/bundle/darwin/LU.py
ipvanish_bundle/bundle/darwin/LV.py
ipvanish_bundle/bundle/darwin/MD.py
ipvanish_bundle/bundle/darwin/MX.py
ipvanish_bundle/bundle/darwin/MY.py
ipvanish_bundle/bundle/darwin/NL.py
ipvanish_bundle/bundle/darwin/NO.py
ipvanish_bundle/bundle/darwin/NZ.py
ipvanish_bundle/bundle/darwin/PH.py
ipvanish_bundle/bundle/darwin/PL.py
ipvanish_bundle/bundle/darwin/PT.py
ipvanish_bundle/bundle/darwin/RO.py
ipvanish_bundle/bundle/darwin/RS.py
ipvanish_bundle/bundle/darwin/SE.py
ipvanish_bundle/bundle/darwin/SG.py
ipvanish_bundle/bundle/darwin/SI.py
ipvanish_bundle/bundle/darwin/SK.py
ipvanish_bundle/bundle/darwin/TR.py
ipvanish_bundle/bundle/darwin/UA.py
ipvanish_bundle/bundle/darwin/UK.py
ipvanish_bundle/bundle/darwin/US.py
ipvanish_bundle/bundle/darwin/ZA.py
ipvanish_bundle/bundle/darwin/__init__.py
ipvanish_bundle-0.1.2.dist-info/LICENSE
ipvanish_bundle-0.1.2.dist-info/METADATA
ipvanish_bundle-0.1.2.dist-info/WHEEL
ipvanish_bundle-0.1.2.dist-info/top_level.txt
ipvanish_bundle-0.1.2.dist-info/RECORD
